ipaymupython/__init__.py
ipaymupython/client.py
ipaymupython/ipaymu.py
python-ipaymu/__init__.py
python-ipaymu/ipaymu.py
python_ipaymu-0.1.3.3.dist-info/LICENSE
python_ipaymu-0.1.3.3.dist-info/METADATA
python_ipaymu-0.1.3.3.dist-info/WHEEL
python_ipaymu-0.1.3.3.dist-info/top_level.txt
python_ipaymu-0.1.3.3.dist-info/RECORD
