Metadata-Version: 2.1
Name: python-ipaymu
Version: 0.1.3.3
Summary: Integrasi iPaymu
Home-page: https://github.com/BayuWardani/python-ipaymu.git
Author: Bayu Wardani
Author-email: bayuwardani51@gmail.com
License: UNKNOWN
Platform: UNKNOWN
Classifier: Development Status :: 4 - Beta
Classifier: Natural Language :: Indonesian
Classifier: Operating System :: Microsoft :: Windows
Classifier: Operating System :: Unix
Classifier: Operating System :: MacOS
Classifier: Programming Language :: Python :: 3 :: Only
